apitalker/__init__.py
apitalker/api.py
apitalker/data.py
apitalker/resources.py
apitalker-1.0.4.dist-info/LICENSE
apitalker-1.0.4.dist-info/METADATA
apitalker-1.0.4.dist-info/WHEEL
apitalker-1.0.4.dist-info/top_level.txt
apitalker-1.0.4.dist-info/RECORD
