Metadata-Version: 2.1
Name: apitalker
Version: 1.0.4
Summary: Python wrapper for using Apitalks API.
Home-page: https://github.com/bednaJedna/att
Author: Radek 'bednaJedna' Bednarik
Author-email: bednarik.radek@gmail.com
License: UNKNOWN
Keywords: api Apitalks wrapper python3 data library utility
Platform: UNKNOWN
Classifier: Development Status :: 5 - Production/Stable
Classifier: Intended Audience :: Developers
Classifier: Intended Audience :: Other Audience
Classifier: License :: OSI Approved :: MIT License
Classifier: Programming Language :: Python :: 3
Classifier: Programming Language :: Python :: 3.8
Classifier: Operating System :: OS Independent
Classifier: Topic :: Software Development :: Libraries
Classifier: Topic :: Software Development :: Libraries :: Python Modules
Classifier: Typing :: Typed
Requires-Dist: requests
Requires-Dist: pandas
